behavython/__init__.py
behavython/behavython_back.py
behavython/behavython_front.py
behavython/behavython_gui.py
behavython/behavython_plot_widget.py
behavython/dlc_helper_functions.py
behavython/logo/VY.ico
behavython/logo/logo.png
behavython-0.6.3.dist-info/LICENSE
behavython-0.6.3.dist-info/METADATA
behavython-0.6.3.dist-info/WHEEL
behavython-0.6.3.dist-info/entry_points.txt
behavython-0.6.3.dist-info/top_level.txt
behavython-0.6.3.dist-info/zip-safe
behavython-0.6.3.dist-info/RECORD
