Metadata-Version: 2.1
Name: behavython
Version: 0.6.3
Summary: To be used in conjunction with Bonsai-RX to extract behavior from video
Home-page: https://github.com/mrdrzit/Behavython
Author: João Pedro & Matheus Costa
Author-email: mcjpedro@gmail.com, matheuscosta3004@gmail.com
License: GPL-3.0
Keywords: plusmaze,openfield,behavior,analysis
License-File: LICENSE
Requires-Dist: deeplabcut[gui,tf]
Requires-Dist: seaborn >=0.13.1
Requires-Dist: pyside6
Requires-Dist: openpyxl
Requires-Dist: scikit-image
Requires-Dist: pandas
Requires-Dist: numpy
Requires-Dist: matplotlib
Requires-Dist: tk
Requires-Dist: scipy
